LICENSE
MANIFEST.in
README.md
setup.py
people_also_ask/__init__.py
people_also_ask/data_collector.py
people_also_ask/exceptions.py
people_also_ask/google.py
people_also_ask/parser.py
people_also_ask/tools.py
people_also_ask.egg-info/PKG-INFO
people_also_ask.egg-info/SOURCES.txt
people_also_ask.egg-info/dependency_links.txt
people_also_ask.egg-info/requires.txt
people_also_ask.egg-info/top_level.txt
people_also_ask/plugins/__init__.py
people_also_ask/plugins/article_generator/__init__.py
people_also_ask/plugins/article_generator/article_generators.py
people_also_ask/request/__init__.py
people_also_ask/request/session.py