Metadata-Version: 2.1
Name: people-also-ask
Version: 1.1.0
Summary: UNKNOWN
Home-page: https://github.com/lagranges/people_also_ask
Author: LE Van Tuan
Author-email: leavantuan2312@gmail.com
License: UNKNOWN
Platform: UNKNOWN
Classifier: Topic :: Software Development :: Libraries :: Python Modules
Classifier: Topic :: Utilities
Classifier: Development Status :: 5 - Production/Stable
Classifier: Operating System :: MacOS
Classifier: Operating System :: Microsoft
Classifier: Programming Language :: Python :: 3.6
Classifier: Programming Language :: Python :: 3.7
Classifier: Programming Language :: Python :: 3.8
Classifier: Typing :: Typed
Requires-Python: >=3.6
License-File: LICENSE
